bot_engine_client/__init__.py
bot_engine_client/enums.py
bot_engine_client/models.py
bot_engine_client-0.1.7.dist-info/WHEEL
bot_engine_client-0.1.7.dist-info/METADATA
bot_engine_client-0.1.7.dist-info/RECORD
