Metadata-Version: 2.1
Name: bot-engine-client
Version: 0.1.7
Summary: A client side library for request data from bot engine server.
License: MIT
Author-email: Mengsyue Amao Tsai <mengsyue.tsai@outlook.com>
Requires-Python: >=3.11
Requires-Dist: richillcapital-http>=0.1.4
